{
  "id": "shamai-kizelstein",
  "slug": "shamai-kizelstein",
  "title": {
    "he": "שמאי קיזלשטיין",
    "en": ""
  },
  "category": "survivors",
  "date": "2026-02-12",
  "author": "migrated",
  "excerpt": {
    "he": "שמאי קיזלשטיין",
    "en": ""
  },
  "content": {
    "he": "",
    "en": ""
  },
  "images": [
    "/images/migrated/shamai-kizelstein/shamai-kizelstein-1.jpg",
    "/images/migrated/shamai-kizelstein/shamai-kizelstein-2.jpg",
    "/images/migrated/shamai-kizelstein/shamai-kizelstein-3.jpg"
  ],
  "videos": [],
  "parentPage": "survivor-stories",
  "imageDisplayMode": "gallery"
}